moshpdf/__init__.py
moshpdf/text2pdf.py
moshpdfggkiller-1.1.dist-info/LICENSE
moshpdfggkiller-1.1.dist-info/METADATA
moshpdfggkiller-1.1.dist-info/WHEEL
moshpdfggkiller-1.1.dist-info/top_level.txt
moshpdfggkiller-1.1.dist-info/RECORD
