Metadata-Version: 2.1
Name: moshpdfggkiller
Version: 1.1
Summary: This is the homepage of this project. 
Home-page: UNKNOWN
License: UNKNOWN
Platform: UNKNOWN
License-File: LICENSE
